binwalk_python_sdk-0.1.3.dist-info/METADATA
binwalk_python_sdk-0.1.3.dist-info/WHEEL
pybinwalk.libs/liblzma-493cb401.so.5
pybinwalk/__init__.py
pybinwalk/_rust.cpython-310-x86_64-linux-gnu.so
pybinwalk/dependencies/__init__.py
pybinwalk/dependencies/manager.py
pybinwalk/dependencies/pip.sh
pybinwalk/dependencies/requirements.txt
pybinwalk/dependencies/src.sh
pybinwalk/dependencies/ubuntu.sh
pybinwalk/main.py
pybinwalk/version.py
binwalk_python_sdk-0.1.3.dist-info/RECORD
