Metadata-Version: 2.4
Name: binwalk-python-sdk
Version: 0.1.3
Summary: Python library for running binwalk
